NiukeQianduanGangweiMianshiZhentiBaodian20212022/README.md
NiukeQianduanGangweiMianshiZhentiBaodian20212022/__init__.py
NiukeQianduanGangweiMianshiZhentiBaodian20212022/__main__.py
NiukeQianduanGangweiMianshiZhentiBaodian20212022/file.epub
NiukeQianduanGangweiMianshiZhentiBaodian20212022/index.html
NiukeQianduanGangweiMianshiZhentiBaodian20212022/css/__init__.py
NiukeQianduanGangweiMianshiZhentiBaodian20212022/css/annotations.css
NiukeQianduanGangweiMianshiZhentiBaodian20212022/css/main.css
NiukeQianduanGangweiMianshiZhentiBaodian20212022/css/normalize.css
NiukeQianduanGangweiMianshiZhentiBaodian20212022/css/popup.css
NiukeQianduanGangweiMianshiZhentiBaodian20212022/font/__init__.py
NiukeQianduanGangweiMianshiZhentiBaodian20212022/font/fontello.eot
NiukeQianduanGangweiMianshiZhentiBaodian20212022/font/fontello.svg
NiukeQianduanGangweiMianshiZhentiBaodian20212022/font/fontello.ttf
NiukeQianduanGangweiMianshiZhentiBaodian20212022/font/fontello.woff
NiukeQianduanGangweiMianshiZhentiBaodian20212022/img/__init__.py
NiukeQianduanGangweiMianshiZhentiBaodian20212022/img/annotator-glyph-sprite.png
NiukeQianduanGangweiMianshiZhentiBaodian20212022/img/annotator-icon-sprite.png
NiukeQianduanGangweiMianshiZhentiBaodian20212022/img/apple-touch-icon.png
NiukeQianduanGangweiMianshiZhentiBaodian20212022/img/cancelfullscreen.png
NiukeQianduanGangweiMianshiZhentiBaodian20212022/img/close.png
NiukeQianduanGangweiMianshiZhentiBaodian20212022/img/fullscreen.png
NiukeQianduanGangweiMianshiZhentiBaodian20212022/img/loader.gif
NiukeQianduanGangweiMianshiZhentiBaodian20212022/img/menu-icon.png
NiukeQianduanGangweiMianshiZhentiBaodian20212022/img/save.png
NiukeQianduanGangweiMianshiZhentiBaodian20212022/img/saved.png
NiukeQianduanGangweiMianshiZhentiBaodian20212022/img/settings-s.png
NiukeQianduanGangweiMianshiZhentiBaodian20212022/img/settings.png
NiukeQianduanGangweiMianshiZhentiBaodian20212022/img/star.png
NiukeQianduanGangweiMianshiZhentiBaodian20212022/js/__init__.py
niuke_qianduan_gangwei_mianshi_zhenti_baodian_2021_2022-2024.3.6.0.dist-info/METADATA
niuke_qianduan_gangwei_mianshi_zhenti_baodian_2021_2022-2024.3.6.0.dist-info/WHEEL
niuke_qianduan_gangwei_mianshi_zhenti_baodian_2021_2022-2024.3.6.0.dist-info/entry_points.txt
niuke_qianduan_gangwei_mianshi_zhenti_baodian_2021_2022-2024.3.6.0.dist-info/top_level.txt
niuke_qianduan_gangwei_mianshi_zhenti_baodian_2021_2022-2024.3.6.0.dist-info/RECORD
